auto_phylo/__init__.py
auto_phylo/__init__.pyi
auto_phylo/commands.json
auto_phylo/pipeliner/__init__.py
auto_phylo/pipeliner/__init__.pyi
auto_phylo/pipeliner/gui.py
auto_phylo/pipeliner/component/AutoPhyloPipeliner.py
auto_phylo/pipeliner/component/ParamConfigurationDialog.py
auto_phylo/pipeliner/component/ParseErrorViewerDialog.py
auto_phylo/pipeliner/component/PipelineDesigner.py
auto_phylo/pipeliner/component/__init__.py
auto_phylo/pipeliner/io/ConfigurationGenerator.py
auto_phylo/pipeliner/io/ConfigurationParser.py
auto_phylo/pipeliner/io/ParseError.py
auto_phylo/pipeliner/io/PipelineGenerator.py
auto_phylo/pipeliner/io/PipelineParser.py
auto_phylo/pipeliner/io/RunFileGenerator.py
auto_phylo/pipeliner/io/RunFileParser.py
auto_phylo/pipeliner/io/__init__.py
auto_phylo/pipeliner/model/Command.py
auto_phylo/pipeliner/model/CommandConfiguration.py
auto_phylo/pipeliner/model/CommandConfigurationEvent.py
auto_phylo/pipeliner/model/Commands.py
auto_phylo/pipeliner/model/Pipeline.py
auto_phylo/pipeliner/model/PipelineChangeEvent.py
auto_phylo/pipeliner/model/PipelineChangeType.py
auto_phylo/pipeliner/model/PipelineConfiguration.py
auto_phylo/pipeliner/model/PipelineConfigurationChangeEvent.py
auto_phylo/pipeliner/model/SpecialNotSupportedError.py
auto_phylo/pipeliner/model/__init__.py
auto_phylo/pipeliner/util/EventListeners.py
auto_phylo/pipeliner/util/Observable.py
auto_phylo/pipeliner/util/__init__.py
auto_phylo_pipeliner-1.0.1.dist-info/LICENSE
auto_phylo_pipeliner-1.0.1.dist-info/METADATA
auto_phylo_pipeliner-1.0.1.dist-info/WHEEL
auto_phylo_pipeliner-1.0.1.dist-info/entry_points.txt
auto_phylo_pipeliner-1.0.1.dist-info/top_level.txt
auto_phylo_pipeliner-1.0.1.dist-info/RECORD
