Metadata-Version: 2.1
Name: auto-phylo-pipeliner
Version: 1.0.1
Summary: A GUI to create auto-phylo pipelines.
Author-email: Jorge Vieira <jbvieira@ibmc.up.pt>, Cristina Vieira <cgvieira@ibmc.up.pt>, Miguel Reboiro-Jato <mrjato@uvigo.gal>, Hugo López-Fernández <hlfernandez@uvigo.gal>
License: Copyright (c) 2023 Jorge Vieira, Cristina Vieira, Hugo López-Fernández,
Project-URL: documentation, http://evolution6.i3s.up.pt/static/auto-phylo/v2/docs/index.html
Project-URL: source, https://github.com/pegi3s/auto-phylo-pipeliner
Project-URL: tracker, https://github.com/pegi3s/auto-phylo-pipeliner/issues
Project-URL: docker, https://hub.docker.com/r/pegi3s/auto-phylo-pipeliner
Keywords: phylogenetics,pipeline,gui
Classifier: Programming Language :: Python :: 3.8
Classifier: License :: OSI Approved :: MIT License
Classifier: Operating System :: OS Independent
Classifier: Development Status :: 5 - Production/Stable
Classifier: Topic :: Scientific/Engineering :: Bio-Informatics
Requires-Python: >=3.8
License-File: LICENSE
Requires-Dist: sv-ttk ==2.5.5
Provides-Extra: dev
Requires-Dist: behave ==1.2.6 ; extra == 'dev'
Requires-Dist: build ==1.0.3 ; extra == 'dev'
Requires-Dist: mypy ==1.5.1 ; extra == 'dev'
Requires-Dist: PyHamcrest ==2.0.4 ; extra == 'dev'
Requires-Dist: pyroma ==4.2 ; extra == 'dev'
Requires-Dist: twine ==4.0.2 ; extra == 'dev'
